cyllene/__init__.py
cyllene-0.0.1.dist-info/METADATA
cyllene-0.0.1.dist-info/WHEEL
cyllene-0.0.1.dist-info/RECORD
